py_hiverunner/__init__.py
py_hiverunner/core/__init__.py
py_hiverunner/core/jvm.py
py_hiverunner/core/parser.py
py_hiverunner/core/type.py
py_hiverunner/hiverunner.py
py_hiverunner/hiverunner_api.py
py_hiverunner/jvm.py
py_hiverunner/parser.py
py_hiverunner/settings.py
py_hiverunner/utils.py
py_hiverunner-0.1.3.dist-info/WHEEL
py_hiverunner-0.1.3.dist-info/METADATA
py_hiverunner-0.1.3.dist-info/RECORD
