Metadata-Version: 2.1
Name: py-hiverunner
Version: 0.1.3
Summary: Python API for unittest Hive applications
Home-page: https://github.com/la9ran9e/py-hiverunner
Keywords: hive,test
Author: la9ran9e
Author-email: tvauritimur@gmail.com
Requires-Python: >=3.6,<4.0
Classifier: Programming Language :: Python :: 3
Classifier: Programming Language :: Python :: 3.6
Classifier: Programming Language :: Python :: 3.7
Classifier: Programming Language :: Python :: 3.8
Requires-Dist: JPype1 (>=0.7.5,<0.8.0)
Requires-Dist: py4j (>=0.10.9,<0.11.0)
Requires-Dist: python-dotenv (>=0.13.0,<0.14.0)
Project-URL: Repository, https://github.com/la9ran9e/py-hiverunner
